variable_polyline_buffer/__init__.py
variable_polyline_buffer/polyline_buffer.py
variable_polyline_buffer-0.1.7.dist-info/LICENSE
variable_polyline_buffer-0.1.7.dist-info/METADATA
variable_polyline_buffer-0.1.7.dist-info/WHEEL
variable_polyline_buffer-0.1.7.dist-info/top_level.txt
variable_polyline_buffer-0.1.7.dist-info/RECORD
