Metadata-Version: 2.1
Name: variable-polyline-buffer
Version: 0.1.7
Summary: A function for calculating a buffer around a polyline, defining the contours of a line with variable thickness.
Home-page: https://github.com/stephtr/variable-polyline-buffer
Author: Stephan Troyer
Author-email: stephantroyer@live.at
License-File: LICENSE
Requires-Dist: numpy
